neuroute/__init__.py
neuroute/client.py
neuroute/exceptions.py
neuroute-0.2.0.dist-info/licenses/LICENSE
neuroute-0.2.0.dist-info/METADATA
neuroute-0.2.0.dist-info/WHEEL
neuroute-0.2.0.dist-info/top_level.txt
neuroute-0.2.0.dist-info/RECORD
