Metadata-Version: 2.4
Name: neuroute
Version: 0.2.0
Summary: Private beta Python SDK for rate-limited AI API access
Author-email: Denny <your.email@example.com>
License: MIT
Project-URL: Homepage, https://github.com/yourusername/ai-social-media-chat-agent
Project-URL: Documentation, https://github.com/yourusername/ai-social-media-chat-agent/blob/main/README.md
Project-URL: Repository, https://github.com/yourusername/ai-social-media-chat-agent
Project-URL: Issues, https://github.com/yourusername/ai-social-media-chat-agent/issues
Keywords: neuroute,ai,sdk,api,chatbot,nlp
Classifier: Development Status :: 3 - Alpha
Classifier: Intended Audience :: Developers
Classifier: License :: OSI Approved :: MIT License
Classifier: Programming Language :: Python :: 3
Classifier: Programming Language :: Python :: 3.9
Classifier: Programming Language :: Python :: 3.10
Classifier: Programming Language :: Python :: 3.11
Classifier: Programming Language :: Python :: 3.12
Requires-Python: >=3.9
License-File: LICENSE
Requires-Dist: requests>=2.31.0
Provides-Extra: dev
Requires-Dist: pytest>=7.0.0; extra == "dev"
Requires-Dist: pytest-cov>=4.0.0; extra == "dev"
Requires-Dist: black>=23.0.0; extra == "dev"
Requires-Dist: flake8>=6.0.0; extra == "dev"
Requires-Dist: build>=1.0.0; extra == "dev"
Requires-Dist: twine>=4.0.0; extra == "dev"
Dynamic: license-file
